neuwo_api/__init__.py
neuwo_api/edge_client.py
neuwo_api/exceptions.py
neuwo_api/logger.py
neuwo_api/models.py
neuwo_api/rest_client.py
neuwo_api/utils.py
neuwo_api-1.0.0.dist-info/licenses/LICENCE
neuwo_api-1.0.0.dist-info/METADATA
neuwo_api-1.0.0.dist-info/WHEEL
neuwo_api-1.0.0.dist-info/top_level.txt
neuwo_api-1.0.0.dist-info/RECORD
