Metadata-Version: 2.4
Name: neuwo_api
Version: 1.0.0
Summary: Neuwo API SDK - Python SDK client for the Neuwo content classification API.
Home-page: https://neuwo.ai
Author: Grzegorz Malisz
Author-email: Grzegorz Malisz <grzegorz.malisz@neuwo.ai>
Maintainer: Grzegorz Malisz
Maintainer-email: Grzegorz Malisz <grzegorz.malisz@neuwo.ai>
License: MIT
Project-URL: Homepage, https://neuwo.ai
Project-URL: Documentation, https://docs.neuwo.ai
Project-URL: Repository, https://github.com/neuwoai/neuwo-api-sdk-python
Keywords: neuwo,api,content,classification,tagging,ai,machine-learning,iab,taxonomy,brand-safety
Classifier: Development Status :: 5 - Production/Stable
Classifier: Intended Audience :: Developers
Classifier: License :: OSI Approved :: MIT License
Classifier: Operating System :: OS Independent
Classifier: Programming Language :: Python :: 3
Classifier: Programming Language :: Python :: 3.8
Classifier: Programming Language :: Python :: 3.9
Classifier: Programming Language :: Python :: 3.10
Classifier: Programming Language :: Python :: 3.11
Classifier: Programming Language :: Python :: 3.12
Classifier: Programming Language :: Python :: 3.13
Classifier: Topic :: Software Development :: Libraries :: Python Modules
Classifier: Topic :: Internet :: WWW/HTTP
Classifier: Typing :: Typed
Requires-Python: >=3.8
License-File: LICENCE
Requires-Dist: requests>=2.25.0
Provides-Extra: dev
Requires-Dist: pytest>=7.0.0; extra == "dev"
Requires-Dist: pytest-cov>=4.0.0; extra == "dev"
Requires-Dist: responses>=0.23.0; extra == "dev"
Requires-Dist: black>=23.0.0; extra == "dev"
Requires-Dist: flake8>=6.0.0; extra == "dev"
Requires-Dist: mypy>=1.0.0; extra == "dev"
Requires-Dist: isort>=5.12.0; extra == "dev"
Requires-Dist: build>=1.0.0; extra == "dev"
Requires-Dist: twine>=4.0.0; extra == "dev"
Provides-Extra: test
Requires-Dist: pytest>=7.0.0; extra == "test"
Requires-Dist: pytest-cov>=4.0.0; extra == "test"
Requires-Dist: responses>=0.23.0; extra == "test"
Dynamic: author
Dynamic: home-page
Dynamic: license-file
Dynamic: maintainer
Dynamic: requires-python
